podman_mcp_server/__init__.py
podman_mcp_server/__main__.py
podman_mcp_server/podman_mcp_server.py
podman_mcp_server-0.0.14.dist-info/METADATA
podman_mcp_server-0.0.14.dist-info/WHEEL
podman_mcp_server-0.0.14.dist-info/entry_points.txt
podman_mcp_server-0.0.14.dist-info/top_level.txt
podman_mcp_server-0.0.14.dist-info/RECORD
