Metadata-Version: 2.4
Name: podman-mcp-server
Version: 0.0.14
Summary: Model Context Protocol (MCP) server for container runtimes (Podman and Docker)
Author-email: Marc Nuri <marc@marcnuri.com>
License-Expression: Apache-2.0
Project-URL: Homepage, https://github.com/manusa/podman-mcp-server
Project-URL: Repository, https://github.com/manusa/podman-mcp-server
Classifier: Programming Language :: Python :: 3
Classifier: Operating System :: OS Independent
Requires-Python: >=3.6
